obs_sd_controls/__init__.py
obs_sd_controls/cli_entry.py
obs_sd_controls/conf.py
obs_sd_controls/config_mgmt.py
obs_sd_controls/obs_controls.py
obs_sd_controls/text_includes.py
obs_sd_controls/thanks.html
obs_sd_controls/thanks.js
obs_sd_controls/twitch_controls.py
sd_controls/__init__.py
sd_controls/cli_tools.py
sd_controls/sd_controls.py
obs_streamdeck_controls-0.2.4.dist-info/LICENSE
obs_streamdeck_controls-0.2.4.dist-info/METADATA
obs_streamdeck_controls-0.2.4.dist-info/WHEEL
obs_streamdeck_controls-0.2.4.dist-info/entry_points.txt
obs_streamdeck_controls-0.2.4.dist-info/top_level.txt
obs_streamdeck_controls-0.2.4.dist-info/RECORD
