Metadata-Version: 2.1
Name: obs-streamdeck-controls
Version: 0.2.4
Summary: A command line tool for controlling OBS Studio via the OBS WebSockets API
Home-page: https://github.com/djnrrd/obs_streamdeck_controls
Author: DJ Nrrd
Author-email: djnrrd@gmail.com
License: UNKNOWN
Project-URL: Bug Tracker, https://github.com/djnrrd/obs_streamdeck_controls/issues
Platform: UNKNOWN
Classifier: License :: OSI Approved :: GNU General Public License v3 (GPLv3)
Classifier: Development Status :: 4 - Beta
Classifier: Environment :: Console
Classifier: Topic :: Games/Entertainment
Classifier: Topic :: Home Automation
Requires-Python: >=3.6
License-File: LICENSE
Requires-Dist: simpleobsws (==0.0.7)
Requires-Dist: appdirs
Requires-Dist: irc
